Workbook
Name Rate_Lauren: OFFSET(Rate!$A$1,MAX(1,COUNTIF(Rate!$C$4:$C$24,Rate!$C$4:$C$24&">0"))-3,2,6,1)
Name Year_Lauren: OFFSET(Rate!$A$1,MAX(1,COUNTIF(Rate!$C$4:$C$24,Rate!$C$4:$C$24&">0"))-3,1,6,1)

Sheet Record
A1: Valuation Date | H1: 43466
A3: Employee Database
A4: ID | B4: Name | C4: Salary | D4: PY Salary | E4: Date of Birth | F4: Date of Hire | G4: Age | H4: Service
A5: 50002 | B5: Woolley,Jeanne M | C5: 99000 | D5: 91000 | E5: 19785 | F5: 42616 | G5: =YEAR($H$1)-YEAR(E5)+(MONTH($H$1)-MONTH(E5))/12+(DAY($H$1)-DAY(E5))/365.25 -> 64.830595 | H5: =ROUND(YEAR($H$1)-YEAR(F5)+(MONTH($H$1)-MONTH(F5))/12+(DAY($H$1)-DAY(F5))/365.25,1) -> 2.3
A6: 50007 | B6: Nelson,Susann | C6: 100000 | D6: 92000 | E6: 20070 | F6: 32743 | G6: =YEAR($H$1)-YEAR(E6)+(MONTH($H$1)-MONTH(E6))/12+(DAY($H$1)-DAY(E6))/365.25 -> 64.053217 | H6: =ROUND(YEAR($H$1)-YEAR(F6)+(MONTH($H$1)-MONTH(F6))/12+(DAY($H$1)-DAY(F6))/365.25,1) -> 29.4
A7: 50004 | B7: Benson,Scott G | C7: 97000 | D7: 89000 | E7: 20341 | F7: 40825 | G7: =YEAR($H$1)-YEAR(E7)+(MONTH($H$1)-MONTH(E7))/12+(DAY($H$1)-DAY(E7))/365.25 -> 63.311431 | H7: =ROUND(YEAR($H$1)-YEAR(F7)+(MONTH($H$1)-MONTH(F7))/12+(DAY($H$1)-DAY(F7))/365.25,1) -> 7.2
A8: 50003 | B8: Bartho,Jerome Fion | C8: 98000 | D8: 90000 | E8: 20584 | F8: 37989 | G8: =YEAR($H$1)-YEAR(E8)+(MONTH($H$1)-MONTH(E8))/12+(DAY($H$1)-DAY(E8))/365.25 -> 62.644764 | H8: =ROUND(YEAR($H$1)-YEAR(F8)+(MONTH($H$1)-MONTH(F8))/12+(DAY($H$1)-DAY(F8))/365.25,1) -> 15
A9: 50009 | B9: Carlson,Robert Lee | C9: 92000 | D9: 84000 | E9: 20694 | F9: 36767 | G9: =YEAR($H$1)-YEAR(E9)+(MONTH($H$1)-MONTH(E9))/12+(DAY($H$1)-DAY(E9))/365.25 -> 62.345483 | H9: =ROUND(YEAR($H$1)-YEAR(F9)+(MONTH($H$1)-MONTH(F9))/12+(DAY($H$1)-DAY(F9))/365.25,1) -> 18.3
A10: 50008 | B10: Asche,Tracy A | C10: 93000 | D10: 85000 | E10: 21491 | F10: 43078 | G10: =YEAR($H$1)-YEAR(E10)+(MONTH($H$1)-MONTH(E10))/12+(DAY($H$1)-DAY(E10))/365.25 -> 60.163929 | H10: =ROUND(YEAR($H$1)-YEAR(F10)+(MONTH($H$1)-MONTH(F10))/12+(DAY($H$1)-DAY(F10))/365.25,1) -> 1.1
A11: 50010 | B11: Donovan,Richard | C11: 91000 | D11: 83000 | E11: 22901 | F11: 32546 | G11: =YEAR($H$1)-YEAR(E11)+(MONTH($H$1)-MONTH(E11))/12+(DAY($H$1)-DAY(E11))/365.25 -> 56.303217 | H11: =ROUND(YEAR($H$1)-YEAR(F11)+(MONTH($H$1)-MONTH(F11))/12+(DAY($H$1)-DAY(F11))/365.25,1) -> 29.9
A12: 50006 | B12: Larson,DeeAnn Smith | C12: 95000 | D12: 87000 | E12: 23072 | F12: 36163 | G12: =YEAR($H$1)-YEAR(E12)+(MONTH($H$1)-MONTH(E12))/12+(DAY($H$1)-DAY(E12))/365.25 -> 55.830595 | H12: =ROUND(YEAR($H$1)-YEAR(F12)+(MONTH($H$1)-MONTH(F12))/12+(DAY($H$1)-DAY(F12))/365.25,1) -> 20
A13: 50001 | B13: Klendshoj,Roxanne | C13: 110000 | D13: 101000 | E13: 26363 | F13: 33665 | G13: =YEAR($H$1)-YEAR(E13)+(MONTH($H$1)-MONTH(E13))/12+(DAY($H$1)-DAY(E13))/365.25 -> 46.822382 | H13: =ROUND(YEAR($H$1)-YEAR(F13)+(MONTH($H$1)-MONTH(F13))/12+(DAY($H$1)-DAY(F13))/365.25,1) -> 26.8
A14: 50005 | B14: Aho,Diane | C14: 96000 | D14: 88000 | E14: 26458 | F14: 40973 | G14: =YEAR($H$1)-YEAR(E14)+(MONTH($H$1)-MONTH(E14))/12+(DAY($H$1)-DAY(E14))/365.25 -> 46.564168 | H14: =ROUND(YEAR($H$1)-YEAR(F14)+(MONTH($H$1)-MONTH(F14))/12+(DAY($H$1)-DAY(F14))/365.25,1) -> 6.8

Sheet Qx
B2: Mortality Table
B3: Age | C3: qx
B4: 5 | C4: 0.000237
B5: =B4+1 -> 6 | C5: 0.000227
B6: =B5+1 -> 7 | C6: 0.000217
B7: =B6+1 -> 8 | C7: 0.000201
B8: =B7+1 -> 9 | C8: 0.000194
B9: =B8+1 -> 10 | C9: 0.000197
B10: =B9+1 -> 11 | C10: 0.000208
B11: =B10+1 -> 12 | C11: 0.000226
B12: =B11+1 -> 13 | C12: 0.000255
B13: =B12+1 -> 14 | C13: 0.000297
B14: =B13+1 -> 15 | C14: 0.000345
B15: =B14+1 -> 16 | C15: 0.000391
B16: =B15+1 -> 17 | C16: 0.00043
... B119: =B118+1 -> 120 | C119: 1

Sheet Rate
B2: Interest Rate | D2: The rate in a year is used to calculate annuity value for the contracts made in that year.
B3: Year | C3: Rate
B4: 2012 | C4: 0.04
B5: 2013 | C5: 0.075
B6: 2014 | C6: 0.065
B7: 2015 | C7: 0.0725
B8: 2016 | C8: 0.065
B9: 2017 | C9: 0.04
B10: 2018 | C10: 0.045 | D10: For example, if a plan is terminated in 2019 and the annuity contract is purchased in the same year, then the rate of 4.00% is used to determine the annuity value.
B11: 2019 | C11: 0.04
B12: 2020
B13: 2021
B14: 2022
B15: 2023
B16: 2024
B17: 2025
B18: 2026
B19: 2027
B20: 2028
B21: 2029
B22: 2030
B23: 2031
B24: 2032
B26: Current Year Info
B27: Contract Year | C27: Rate
B28: 2019 | C28: =VLOOKUP(B28,B4:C24,2) -> 0.04

Sheet Annuity
B2: Life Annuity
B3: Current Age | G3: =Statement!E12 -> 46
B4: Annual Benefit | G4: =Statement!E16 -> 4540.8
B5: Interest Rate | G5: =Rate!C28 -> 0.04
B7: Contract Year | G7: =Rate!B28 -> 2019
B8: Annuity Factor | G8: =SUM(G13:G87) -> 18.6835
B9: Annuity Value | G9: =G8*G4 -> 84838.037
B11: Excel Calculation
B12: Age | C12: Qx | D12: px | E12: tpx | G12: Discount value
B13: =$G$3 -> 46 | C13: =IF(B13="","",VLOOKUP(B13,Qx!$B$4:$C$119,2)) -> 0.001722 | D13: =IF(B14="","", ROUND(1-C13,6)) -> 0.998278 | E13: =C13+D13 -> 1 | G13: =IF(B13="","",ROUND((E13/(1+$G$5)^(B13-$B$13)),4)) -> 1
B14: =IF((OR(B13=120, B13="")),"", B13+1) -> 47 | C14: =IF(B14="","",VLOOKUP(B14,Qx!$B$4:$C$119,2)) -> 0.001899 | D14: =IF(B15="","", ROUND(1-C14,6)) -> 0.998101 | E14: =IF(B14="","",ROUND((D13*E13),6)) -> 0.998278 | G14: =IF(B14="","",ROUND((E14/(1+$G$5)^(B14-$B$13)),4)) -> 0.9599
B15: =IF((OR(B14=120, B14="")),"", B14+1) -> 48 | C15: =IF(B15="","",VLOOKUP(B15,Qx!$B$4:$C$119,2)) -> 0.002102 | D15: =IF(B16="","", ROUND(1-C15,6)) -> 0.997898 | E15: =IF(B15="","",ROUND((D14*E14),6)) -> 0.996382 | G15: =IF(B15="","",ROUND((E15/(1+$G$5)^(B15-$B$13)),4)) -> 0.9212
B16: =IF((OR(B15=120, B15="")),"", B15+1) -> 49 | C16: =IF(B16="","",VLOOKUP(B16,Qx!$B$4:$C$119,2)) -> 0.002326 | D16: =IF(B17="","", ROUND(1-C16,6)) -> 0.997674 | E16: =IF(B16="","",ROUND((D15*E15),6)) -> 0.994288 | G16: =IF(B16="","",ROUND((E16/(1+$G$5)^(B16-$B$13)),4)) -> 0.8839
B17: =IF((OR(B16=120, B16="")),"", B16+1) -> 50 | C17: =IF(B17="","",VLOOKUP(B17,Qx!$B$4:$C$119,2)) -> 0.002579 | D17: =IF(B18="","", ROUND(1-C17,6)) -> 0.997421 | E17: =IF(B17="","",ROUND((D16*E16),6)) -> 0.991975 | G17: =IF(B17="","",ROUND((E17/(1+$G$5)^(B17-$B$13)),4)) -> 0.8479
B18: =IF((OR(B17=120, B17="")),"", B17+1) -> 51 | C18: =IF(B18="","",VLOOKUP(B18,Qx!$B$4:$C$119,2)) -> 0.002872 | D18: =IF(B19="","", ROUND(1-C18,6)) -> 0.997128 | E18: =IF(B18="","",ROUND((D17*E17),6)) -> 0.989417 | G18: =IF(B18="","",ROUND((E18/(1+$G$5)^(B18-$B$13)),4)) -> 0.8132
B19: =IF((OR(B18=120, B18="")),"", B18+1) -> 52 | C19: =IF(B19="","",VLOOKUP(B19,Qx!$B$4:$C$119,2)) -> 0.003213 | D19: =IF(B20="","", ROUND(1-C19,6)) -> 0.996787 | E19: =IF(B19="","",ROUND((D18*E18),6)) -> 0.986575 | G19: =IF(B19="","",ROUND((E19/(1+$G$5)^(B19-$B$13)),4)) -> 0.7797
B20: =IF((OR(B19=120, B19="")),"", B19+1) -> 53 | C20: =IF(B20="","",VLOOKUP(B20,Qx!$B$4:$C$119,2)) -> 0.003584 | D20: =IF(B21="","", ROUND(1-C20,6)) -> 0.996416 | E20: =IF(B20="","",ROUND((D19*E19),6)) -> 0.983405 | G20: =IF(B20="","",ROUND((E20/(1+$G$5)^(B20-$B$13)),4)) -> 0.7473
B21: =IF((OR(B20=120, B20="")),"", B20+1) -> 54 | C21: =IF(B21="","",VLOOKUP(B21,Qx!$B$4:$C$119,2)) -> 0.003979 | D21: =IF(B22="","", ROUND(1-C21,6)) -> 0.996021 | E21: =IF(B21="","",ROUND((D20*E20),6)) -> 0.97988 | G21: =IF(B21="","",ROUND((E21/(1+$G$5)^(B21-$B$13)),4)) -> 0.716
B22: =IF((OR(B21=120, B21="")),"", B21+1) -> 55 | C22: =IF(B22="","",VLOOKUP(B22,Qx!$B$4:$C$119,2)) -> 0.004425 | D22: =IF(B23="","", ROUND(1-C22,6)) -> 0.995575 | E22: =IF(B22="","",ROUND((D21*E21),6)) -> 0.975981 | G22: =IF(B22="","",ROUND((E22/(1+$G$5)^(B22-$B$13)),4)) -> 0.6857
B23: =IF((OR(B22=120, B22="")),"", B22+1) -> 56 | C23: =IF(B23="","",VLOOKUP(B23,Qx!$B$4:$C$119,2)) -> 0.004949 | D23: =IF(B24="","", ROUND(1-C23,6)) -> 0.995051 | E23: =IF(B23="","",ROUND((D22*E22),6)) -> 0.971662 | G23: =IF(B23="","",ROUND((E23/(1+$G$5)^(B23-$B$13)),4)) -> 0.6564
B24: =IF((OR(B23=120, B23="")),"", B23+1) -> 57 | C24: =IF(B24="","",VLOOKUP(B24,Qx!$B$4:$C$119,2)) -> 0.005581 | D24: =IF(B25="","", ROUND(1-C24,6)) -> 0.994419 | E24: =IF(B24="","",ROUND((D23*E23),6)) -> 0.966853 | G24: =IF(B24="","",ROUND((E24/(1+$G$5)^(B24-$B$13)),4)) -> 0.628
B25: =IF((OR(B24=120, B24="")),"", B24+1) -> 58 | C25: =IF(B25="","",VLOOKUP(B25,Qx!$B$4:$C$119,2)) -> 0.0063 | D25: =IF(B26="","", ROUND(1-C25,6)) -> 0.9937 | E25: =IF(B25="","",ROUND((D24*E24),6)) -> 0.961457 | G25: =IF(B25="","",ROUND((E25/(1+$G$5)^(B25-$B$13)),4)) -> 0.6005
... B87: =IF((OR(B86=120, B86="")),"", B86+1) -> 120 | C87: =IF(B87="","",VLOOKUP(B87,Qx!$B$4:$C$119,2)) -> 1 | D87: =IF(B88="","", ROUND(1-C87,6)) | E87: =IF(B87="","",ROUND((D86*E86),6)) -> 1e-06 | G87: =IF(B87="","",ROUND((E87/(1+$G$5)^(B87-$B$13)),4)) -> 0
B88: =IF((OR(B87=120, B87="")),"", B87+1)
B89: =IF((OR(B88=120, B88="")),"", B88+1)
B90: =IF((OR(B89=120, B89="")),"", B89+1)
B91: =IF((OR(B90=120, B90="")),"", B90+1)
B92: =IF((OR(B91=120, B91="")),"", B91+1)
B93: =IF((OR(B92=120, B92="")),"", B92+1)
B94: =IF((OR(B93=120, B93="")),"", B93+1)
B95: =IF((OR(B94=120, B94="")),"", B94+1)
B96: =IF((OR(B95=120, B95="")),"", B95+1)
B97: =IF((OR(B96=120, B96="")),"", B96+1)
B98: =IF((OR(B97=120, B97="")),"", B97+1)
B99: =IF((OR(B98=120, B98="")),"", B98+1)
... B133: =IF((OR(B132=120, B132="")),"", B132+1)

Sheet Statement
C3: Benefit Statement
C5: Name | E5: =IF(ISNUMBER(FIND(" ",(VLOOKUP(E26,Record!A4:H14,2,FALSE)))),MID(VLOOKUP(E26,Record!A4:H14,2,FALSE),FIND(",",VLOOKUP(E26,Record!A4:H14,2,FALSE))+1,FIND(" ",VLOOKUP(E26,Record!A4:H14,2,FALSE))-FIND(",",VLOOKUP(E26,Record!A4:H14,2,FALSE)))&MID(VLOOKUP(E26,Record!A4:H14,2,FALSE),1,FIND(",",VLOOKUP(E26,Record!A4:H14,2,FALSE))-1),RIGHT(VLOOKUP(E26,Record!A4:H14,2,FALSE), LEN(VLOOKUP(E26,Record!A4:H14,2,FALSE))-FIND(",",VLOOKUP(E26,Record!A4:H14,2,FALSE)))&" "&LEFT(VLOOKUP(E26,Record!A4:H14,2,FALSE),FIND(",",VLOOKUP(E26,Record!A4:H14,2,FALSE))-1)) -> Diane Aho
C7: Date of Birth | E7: =VLOOKUP($E$26,Record!$A$4:$H$14,5,FALSE) -> 26458
C8: Date of Hire | E8: =VLOOKUP($E$26,Record!$A$4:$H$14,6,FALSE) -> 40973
C9: Date of Participation | E9: =IF(ABS(MONTH(EOMONTH(E8-1,12)+1)-MONTH(E8))>=6, EDATE(EOMONTH(EDATE(E8,12),-MONTH(EDATE(E8,12)))+1,12), EOMONTH(EDATE(E8,12),-MONTH(EDATE(E8,12))+6)+1) -> 41456
C10: Date of Normal Retirement | E10: =EOMONTH(MAX(EDATE(E7,12*65),EDATE(E8,12*5)), 0)+1 -> 50222
C11: Salary | E11: =VLOOKUP($E$26,Record!$A$4:$H$14,3,FALSE) -> 96000
C12: Age last birthday | E12: =YEAR(Record!H1)-YEAR(E7)-IF(Record!H1<DATE(YEAR(Record!H1), MONTH(E7), DAY(E7)),1,0) -> 46
C13: Service since the participation date | E13: =(YEAR(E9)-YEAR(Record!H1))/12+(MONTH(E9)-MONTH(Record!H1)) -> 5.5
C14: Annual Benefit | E14: =0.02*E11*E13 -> 10560
C15: Early Retirement factor | E15: =IF(1-0.03*(YEAR(E10)-YEAR(Record!H1)+IF(E10<DATE(YEAR(E10), MONTH(Record!H1), DAY(Record!H1)),0,1))>0, 1-0.03*(YEAR(E10)-YEAR(Record!H1)+IF(E10<DATE(YEAR(E10), MONTH(Record!H1), DAY(Record!H1)),0,1)), 0) -> 0.43
C16: Early Retirement Benefit | E16: =E14*E15 -> 4540.8
C17: Annuity purchase value | E17: =Annuity!G9 -> 84838.037
C19: Retirement Goal | E19: =E11*10 -> 960000
C20: Achieved Goal Percentage | E20: =E17/E19 -> 0.088372955
C23: ="The statement is prepared on "&TEXT(WORKDAY(DATE(YEAR(Record!H1),5,1),7),"MMMM DD, YYYY") -> The statement is prepared on May 10, 2019
C26: Identification Number --- input item | E26: 50005

Sheet Pivot Table
B2: Age by Service Table with total Salaries plus total PY Salaries
D5: Serv
B6: Age | C6: Values | D6: 0-5 | E6: 6-10 | F6: 11-20 | G6: 20+ | H6: Grand Total
B7: 45-50 | C7: Sum of Field1 | D7: 0 | E7: 184000 | F7: 0 | G7: 211000 | H7: 395000
C8: Count of Age | E8: 1 | G8: 1 | H8: 2
B9: 55-60 | C9: Sum of Field1 | D9: 0 | E9: 0 | F9: 182000 | G9: 174000 | H9: 356000
C10: Count of Age | F10: 1 | G10: 1 | H10: 2
B11: 60-65 | C11: Sum of Field1 | D11: 368000 | E11: 186000 | F11: 364000 | G11: 192000 | H11: 1110000
C12: Count of Age | D12: 2 | E12: 1 | F12: 2 | G12: 1 | H12: 6

Sheet Sort DB
A1: Valuation Date | H1: 43466
A3: Employee Database
A4: ID | B4: Name | C4: Salary | D4: PY Salary | E4: Date of Birth | F4: Date of Hire | G4: Age | H4: Service
A5: 50002 | B5: Woolley,Jeanne M | C5: 99000 | D5: 91000 | E5: 19785 | F5: 42616 | G5: =YEAR($H$1)-YEAR(E5)+(MONTH($H$1)-MONTH(E5))/12+(DAY($H$1)-DAY(E5))/365.25 -> 64.830595 | H5: =ROUND(YEAR($H$1)-YEAR(F5)+(MONTH($H$1)-MONTH(F5))/12+(DAY($H$1)-DAY(F5))/365.25,1) -> 2.3
A6: 50007 | B6: Nelson,Susann | C6: 100000 | D6: 92000 | E6: 20070 | F6: 32743 | G6: =YEAR($H$1)-YEAR(E6)+(MONTH($H$1)-MONTH(E6))/12+(DAY($H$1)-DAY(E6))/365.25 -> 64.053217 | H6: =ROUND(YEAR($H$1)-YEAR(F6)+(MONTH($H$1)-MONTH(F6))/12+(DAY($H$1)-DAY(F6))/365.25,1) -> 29.4
A7: 50004 | B7: Benson,Scott G | C7: 97000 | D7: 89000 | E7: 20341 | F7: 40825 | G7: =YEAR($H$1)-YEAR(E7)+(MONTH($H$1)-MONTH(E7))/12+(DAY($H$1)-DAY(E7))/365.25 -> 63.311431 | H7: =ROUND(YEAR($H$1)-YEAR(F7)+(MONTH($H$1)-MONTH(F7))/12+(DAY($H$1)-DAY(F7))/365.25,1) -> 7.2
A8: 50003 | B8: Bartho,Jerome Fion | C8: 98000 | D8: 90000 | E8: 20584 | F8: 37989 | G8: =YEAR($H$1)-YEAR(E8)+(MONTH($H$1)-MONTH(E8))/12+(DAY($H$1)-DAY(E8))/365.25 -> 62.644764 | H8: =ROUND(YEAR($H$1)-YEAR(F8)+(MONTH($H$1)-MONTH(F8))/12+(DAY($H$1)-DAY(F8))/365.25,1) -> 15
A9: 50009 | B9: Carlson,Robert Lee | C9: 92000 | D9: 84000 | E9: 20694 | F9: 36767 | G9: =YEAR($H$1)-YEAR(E9)+(MONTH($H$1)-MONTH(E9))/12+(DAY($H$1)-DAY(E9))/365.25 -> 62.345483 | H9: =ROUND(YEAR($H$1)-YEAR(F9)+(MONTH($H$1)-MONTH(F9))/12+(DAY($H$1)-DAY(F9))/365.25,1) -> 18.3
A10: 50008 | B10: Asche,Tracy A | C10: 93000 | D10: 85000 | E10: 21491 | F10: 43078 | G10: =YEAR($H$1)-YEAR(E10)+(MONTH($H$1)-MONTH(E10))/12+(DAY($H$1)-DAY(E10))/365.25 -> 60.163929 | H10: =ROUND(YEAR($H$1)-YEAR(F10)+(MONTH($H$1)-MONTH(F10))/12+(DAY($H$1)-DAY(F10))/365.25,1) -> 1.1
A11: 50010 | B11: Donovan,Richard | C11: 91000 | D11: 83000 | E11: 22901 | F11: 32546 | G11: =YEAR($H$1)-YEAR(E11)+(MONTH($H$1)-MONTH(E11))/12+(DAY($H$1)-DAY(E11))/365.25 -> 56.303217 | H11: =ROUND(YEAR($H$1)-YEAR(F11)+(MONTH($H$1)-MONTH(F11))/12+(DAY($H$1)-DAY(F11))/365.25,1) -> 29.9
A12: 50006 | B12: Larson,DeeAnn Smith | C12: 95000 | D12: 87000 | E12: 23072 | F12: 36163 | G12: =YEAR($H$1)-YEAR(E12)+(MONTH($H$1)-MONTH(E12))/12+(DAY($H$1)-DAY(E12))/365.25 -> 55.830595 | H12: =ROUND(YEAR($H$1)-YEAR(F12)+(MONTH($H$1)-MONTH(F12))/12+(DAY($H$1)-DAY(F12))/365.25,1) -> 20
A13: 50001 | B13: Klendshoj,Roxanne | C13: 110000 | D13: 101000 | E13: 26363 | F13: 33665 | G13: =YEAR($H$1)-YEAR(E13)+(MONTH($H$1)-MONTH(E13))/12+(DAY($H$1)-DAY(E13))/365.25 -> 46.822382 | H13: =ROUND(YEAR($H$1)-YEAR(F13)+(MONTH($H$1)-MONTH(F13))/12+(DAY($H$1)-DAY(F13))/365.25,1) -> 26.8
A14: 50005 | B14: Aho,Diane | C14: 96000 | D14: 88000 | E14: 26458 | F14: 40973 | G14: =YEAR($H$1)-YEAR(E14)+(MONTH($H$1)-MONTH(E14))/12+(DAY($H$1)-DAY(E14))/365.25 -> 46.564168 | H14: =ROUND(YEAR($H$1)-YEAR(F14)+(MONTH($H$1)-MONTH(F14))/12+(DAY($H$1)-DAY(F14))/365.25,1) -> 6.8

Sheet Filter Advance
A1: Valuation Date | H1: 43466
B3: Summary Information | J3: Filter Criteria
B4: • Number of Records | D4: =COUNT(A10:A19) -> 10 | F4: • Maximum age | G4: =MAX(G10:G19) -> 64.830595 | J4: Age | K4: Salary
B5: • Total salary of current year | D5: =SUM(C10:C19) -> 971000 | F5: • Minimum age | G5: =MIN(G10:G19) -> 46.564168 | J5: >50 | K5: >80000
B6: • Average salary of current year | D6: =AVERAGE(C10:C19) -> 97100 | F6: • Average service | G6: =AVERAGE(H10:H19) -> 15.685298 | J6: <40 | K6: >80000
A8: Employee Database
A9: ID | B9: Name | C9: Salary | D9: PY Salary | E9: Date of Birth | F9: Date of Hire | G9: Age | H9: Service
A10: 50002 | B10: Woolley,Jeanne M | C10: 99000 | D10: 91000 | E10: 19785 | F10: 42616 | G10: =YEAR($H$1)-YEAR(E10)+(MONTH($H$1)-MONTH(E10))/12+(DAY($H$1)-DAY(E10))/365.25 -> 64.830595 | H10: =ROUND(YEAR($H$1)-YEAR(F10)+(MONTH($H$1)-MONTH(F10))/12+(DAY($H$1)-DAY(F10))/365.25,1) -> 2.3
A11: 50007 | B11: Nelson,Susann | C11: 100000 | D11: 92000 | E11: 20070 | F11: 32743 | G11: =YEAR($H$1)-YEAR(E11)+(MONTH($H$1)-MONTH(E11))/12+(DAY($H$1)-DAY(E11))/365.25 -> 64.053217 | H11: =ROUND(YEAR($H$1)-YEAR(F11)+(MONTH($H$1)-MONTH(F11))/12+(DAY($H$1)-DAY(F11))/365.25,1) -> 29.4
A12: 50004 | B12: Benson,Scott G | C12: 97000 | D12: 89000 | E12: 20341 | F12: 40825 | G12: =YEAR($H$1)-YEAR(E12)+(MONTH($H$1)-MONTH(E12))/12+(DAY($H$1)-DAY(E12))/365.25 -> 63.311431 | H12: =ROUND(YEAR($H$1)-YEAR(F12)+(MONTH($H$1)-MONTH(F12))/12+(DAY($H$1)-DAY(F12))/365.25,1) -> 7.2
A13: 50003 | B13: Bartho,Jerome Fion | C13: 98000 | D13: 90000 | E13: 20584 | F13: 37989 | G13: =YEAR($H$1)-YEAR(E13)+(MONTH($H$1)-MONTH(E13))/12+(DAY($H$1)-DAY(E13))/365.25 -> 62.644764 | H13: =ROUND(YEAR($H$1)-YEAR(F13)+(MONTH($H$1)-MONTH(F13))/12+(DAY($H$1)-DAY(F13))/365.25,1) -> 15
A14: 50009 | B14: Carlson,Robert Lee | C14: 92000 | D14: 84000 | E14: 20694 | F14: 36767 | G14: =YEAR($H$1)-YEAR(E14)+(MONTH($H$1)-MONTH(E14))/12+(DAY($H$1)-DAY(E14))/365.25 -> 62.345483 | H14: =ROUND(YEAR($H$1)-YEAR(F14)+(MONTH($H$1)-MONTH(F14))/12+(DAY($H$1)-DAY(F14))/365.25,1) -> 18.3
A15: 50008 | B15: Asche,Tracy A | C15: 93000 | D15: 85000 | E15: 21491 | F15: 43078 | G15: =YEAR($H$1)-YEAR(E15)+(MONTH($H$1)-MONTH(E15))/12+(DAY($H$1)-DAY(E15))/365.25 -> 60.163929 | H15: =ROUND(YEAR($H$1)-YEAR(F15)+(MONTH($H$1)-MONTH(F15))/12+(DAY($H$1)-DAY(F15))/365.25,1) -> 1.1
A16: 50010 | B16: Donovan,Richard | C16: 91000 | D16: 83000 | E16: 22901 | F16: 32546 | G16: =YEAR($H$1)-YEAR(E16)+(MONTH($H$1)-MONTH(E16))/12+(DAY($H$1)-DAY(E16))/365.25 -> 56.303217 | H16: =ROUND(YEAR($H$1)-YEAR(F16)+(MONTH($H$1)-MONTH(F16))/12+(DAY($H$1)-DAY(F16))/365.25,1) -> 29.9
A17: 50006 | B17: Larson,DeeAnn Smith | C17: 95000 | D17: 87000 | E17: 23072 | F17: 36163 | G17: =YEAR($H$1)-YEAR(E17)+(MONTH($H$1)-MONTH(E17))/12+(DAY($H$1)-DAY(E17))/365.25 -> 55.830595 | H17: =ROUND(YEAR($H$1)-YEAR(F17)+(MONTH($H$1)-MONTH(F17))/12+(DAY($H$1)-DAY(F17))/365.25,1) -> 20
A18: 50001 | B18: Klendshoj,Roxanne | C18: 110000 | D18: 101000 | E18: 26363 | F18: 33665 | G18: =YEAR($H$1)-YEAR(E18)+(MONTH($H$1)-MONTH(E18))/12+(DAY($H$1)-DAY(E18))/365.25 -> 46.822382 | H18: =YEAR($H$1)-YEAR(F18)+(MONTH($H$1)-MONTH(F18))/12+(DAY($H$1)-DAY(F18))/365.25 -> 26.830595
A19: 50005 | B19: Aho,Diane | C19: 96000 | D19: 88000 | E19: 26458 | F19: 40973 | G19: =YEAR($H$1)-YEAR(E19)+(MONTH($H$1)-MONTH(E19))/12+(DAY($H$1)-DAY(E19))/365.25 -> 46.564168 | H19: =YEAR($H$1)-YEAR(F19)+(MONTH($H$1)-MONTH(F19))/12+(DAY($H$1)-DAY(F19))/365.25 -> 6.8223819

Sheet Filter DB
A1: Valuation Date | H1: 43466
B3: Summary Information
B4: • Number of Records | D4: =COUNT(A10:A19) -> 10 | F4: • Maximum age | G4: =MAX(G10:G19) -> 64.830595
B5: • Total salary of current year | D5: =SUM(C10:C19) -> 971000 | F5: • Minimum age | G5: =MIN(G10:G19) -> 46.564168
B6: • Average salary of current year | D6: =AVERAGE(C10:C19) -> 97100 | F6: • Average service | G6: =AVERAGE(H10:H19) -> 15.68
A8: Employee Database
A9: ID | B9: Name | C9: Salary | D9: PY Salary | E9: Date of Birth | F9: Date of Hire | G9: Age | H9: Service
A10: 50002 | B10: Woolley,Jeanne M | C10: 99000 | D10: 91000 | E10: 19785 | F10: 42616 | G10: =YEAR($H$1)-YEAR(E10)+(MONTH($H$1)-MONTH(E10))/12+(DAY($H$1)-DAY(E10))/365.25 -> 64.830595 | H10: =ROUND(YEAR($H$1)-YEAR(F10)+(MONTH($H$1)-MONTH(F10))/12+(DAY($H$1)-DAY(F10))/365.25,1) -> 2.3
A11: 50007 | B11: Nelson,Susann | C11: 100000 | D11: 92000 | E11: 20070 | F11: 32743 | G11: =YEAR($H$1)-YEAR(E11)+(MONTH($H$1)-MONTH(E11))/12+(DAY($H$1)-DAY(E11))/365.25 -> 64.053217 | H11: =ROUND(YEAR($H$1)-YEAR(F11)+(MONTH($H$1)-MONTH(F11))/12+(DAY($H$1)-DAY(F11))/365.25,1) -> 29.4
A12: 50004 | B12: Benson,Scott G | C12: 97000 | D12: 89000 | E12: 20341 | F12: 40825 | G12: =YEAR($H$1)-YEAR(E12)+(MONTH($H$1)-MONTH(E12))/12+(DAY($H$1)-DAY(E12))/365.25 -> 63.311431 | H12: =ROUND(YEAR($H$1)-YEAR(F12)+(MONTH($H$1)-MONTH(F12))/12+(DAY($H$1)-DAY(F12))/365.25,1) -> 7.2
A13: 50003 | B13: Bartho,Jerome Fion | C13: 98000 | D13: 90000 | E13: 20584 | F13: 37989 | G13: =YEAR($H$1)-YEAR(E13)+(MONTH($H$1)-MONTH(E13))/12+(DAY($H$1)-DAY(E13))/365.25 -> 62.644764 | H13: =ROUND(YEAR($H$1)-YEAR(F13)+(MONTH($H$1)-MONTH(F13))/12+(DAY($H$1)-DAY(F13))/365.25,1) -> 15
A14: 50009 | B14: Carlson,Robert Lee | C14: 92000 | D14: 84000 | E14: 20694 | F14: 36767 | G14: =YEAR($H$1)-YEAR(E14)+(MONTH($H$1)-MONTH(E14))/12+(DAY($H$1)-DAY(E14))/365.25 -> 62.345483 | H14: =ROUND(YEAR($H$1)-YEAR(F14)+(MONTH($H$1)-MONTH(F14))/12+(DAY($H$1)-DAY(F14))/365.25,1) -> 18.3
A15: 50008 | B15: Asche,Tracy A | C15: 93000 | D15: 85000 | E15: 21491 | F15: 43078 | G15: =YEAR($H$1)-YEAR(E15)+(MONTH($H$1)-MONTH(E15))/12+(DAY($H$1)-DAY(E15))/365.25 -> 60.163929 | H15: =ROUND(YEAR($H$1)-YEAR(F15)+(MONTH($H$1)-MONTH(F15))/12+(DAY($H$1)-DAY(F15))/365.25,1) -> 1.1
A16: 50010 | B16: Donovan,Richard | C16: 91000 | D16: 83000 | E16: 22901 | F16: 32546 | G16: =YEAR($H$1)-YEAR(E16)+(MONTH($H$1)-MONTH(E16))/12+(DAY($H$1)-DAY(E16))/365.25 -> 56.303217 | H16: =ROUND(YEAR($H$1)-YEAR(F16)+(MONTH($H$1)-MONTH(F16))/12+(DAY($H$1)-DAY(F16))/365.25,1) -> 29.9
A17: 50006 | B17: Larson,DeeAnn Smith | C17: 95000 | D17: 87000 | E17: 23072 | F17: 36163 | G17: =YEAR($H$1)-YEAR(E17)+(MONTH($H$1)-MONTH(E17))/12+(DAY($H$1)-DAY(E17))/365.25 -> 55.830595 | H17: =ROUND(YEAR($H$1)-YEAR(F17)+(MONTH($H$1)-MONTH(F17))/12+(DAY($H$1)-DAY(F17))/365.25,1) -> 20
A18: 50001 | B18: Klendshoj,Roxanne | C18: 110000 | D18: 101000 | E18: 26363 | F18: 33665 | G18: =YEAR($H$1)-YEAR(E18)+(MONTH($H$1)-MONTH(E18))/12+(DAY($H$1)-DAY(E18))/365.25 -> 46.822382 | H18: =ROUND(YEAR($H$1)-YEAR(F18)+(MONTH($H$1)-MONTH(F18))/12+(DAY($H$1)-DAY(F18))/365.25,1) -> 26.8
A19: 50005 | B19: Aho,Diane | C19: 96000 | D19: 88000 | E19: 26458 | F19: 40973 | G19: =YEAR($H$1)-YEAR(E19)+(MONTH($H$1)-MONTH(E19))/12+(DAY($H$1)-DAY(E19))/365.25 -> 46.564168 | H19: =ROUND(YEAR($H$1)-YEAR(F19)+(MONTH($H$1)-MONTH(F19))/12+(DAY($H$1)-DAY(F19))/365.25,1) -> 6.8
